mlduct/__init__.py
mlduct-0.0.0.6.dist-info/LICENSE
mlduct-0.0.0.6.dist-info/METADATA
mlduct-0.0.0.6.dist-info/WHEEL
mlduct-0.0.0.6.dist-info/top_level.txt
mlduct-0.0.0.6.dist-info/RECORD
